TextProcess/TextProcess.py
TextProcess/__init__.py
TextProcess/langconv.py
TextProcess/zh_wiki.py
TextProcess/emoji/__init__.py
TextProcess/emoji/core.py
TextProcess/emoji/unicode_codes.py
TextProcess_bak/__init__.py
TextProcess_bak/langconv.py
TextProcess_bak/textprocess.py
TextProcess_bak/zh_wiki.py
TextProcess_bak/emoji/__init__.py
TextProcess_bak/emoji/core.py
TextProcess_bak/emoji/unicode_codes.py
TextProcess_old/TextProcess.py
TextProcess_old/__init__.py
TextProcess_old/langconv.py
TextProcess_old/zh_wiki.py
TextProcess_old/emoji/__init__.py
TextProcess_old/emoji/core.py
TextProcess_old/emoji/unicode_codes.py
TextProcess_Ora-0.0.6.dist-info/LICENSE
TextProcess_Ora-0.0.6.dist-info/METADATA
TextProcess_Ora-0.0.6.dist-info/WHEEL
TextProcess_Ora-0.0.6.dist-info/top_level.txt
TextProcess_Ora-0.0.6.dist-info/RECORD
