Metadata-Version: 2.1
Name: TextProcess-Ora
Version: 0.0.6
Summary: compute similar scores of two text
Home-page: https://github.com/shawshany/TextProcess
Author: Ora
Author-email: victor.xsyang@gmail.com
License: UNKNOWN
Platform: UNKNOWN
Classifier: Programming Language :: Python :: 2
Classifier: Programming Language :: Python :: 3
Classifier: License :: OSI Approved :: MIT License
Classifier: Operating System :: OS Independent
Requires-Python: >=2.7
